README.md
setup.py
PyTls/Chinese2num.py
PyTls/StrBuffer.py
PyTls/__init__.py
PyTls/dictt.py
PyTls/listt.py
PyTls/loaddatat.py
PyTls/matht.py
PyTls/randomt.py
PyTls/strt.py
PyTls/textt.py
PyTls/trickt.py
PyTls/typet.py
PyTls/wrappert.py
PyTls.egg-info/PKG-INFO
PyTls.egg-info/SOURCES.txt
PyTls.egg-info/dependency_links.txt
PyTls.egg-info/requires.txt
PyTls.egg-info/top_level.txt