Metadata-Version: 1.2
Name: PyTls
Version: 0.0.8
Summary: python tools, we need something fast and easy
Home-page: https://github.com/sladesha
Author: sladesal
Author-email: stw386@sina.com
Maintainer: sladesal
Maintainer-email: stw386@sina.com
License: MIT License
Platform: all
Classifier: Operating System :: OS Independent
Classifier: Intended Audience :: Developers
Classifier: License :: OSI Approved :: BSD License
Classifier: Programming Language :: Python
Classifier: Programming Language :: Python :: Implementation
Classifier: Programming Language :: Python :: 2
Classifier: Programming Language :: Python :: 2.7
Classifier: Programming Language :: Python :: 3
Classifier: Programming Language :: Python :: 3.4
Classifier: Programming Language :: Python :: 3.5
Classifier: Programming Language :: Python :: 3.6
Classifier: Topic :: Software Development :: Libraries
